titiler/image/__init__.py
titiler/image/dependencies.py
titiler/image/factory.py
titiler/image/main.py
titiler/image/models.py
titiler/image/reader.py
titiler/image/resources/enums.py
titiler/image/settings.py
titiler/image/templates/iiif.html
titiler/image/templates/local.html
titiler/image/utils.py
titiler.image-0.1.0.dist-info/WHEEL
titiler.image-0.1.0.dist-info/METADATA
titiler.image-0.1.0.dist-info/licenses/LICENSE
titiler.image-0.1.0.dist-info/RECORD
