Metadata-Version: 2.1
Name: titiler.image
Version: 0.1.0
Summary: TiTiler extension to work with non-geo images.
License: MIT
Keywords: TiTiler,IIIF,DeepZoom,Fastapi
Author-email: Vincent Sarago <vincent@developmentseed.com>
Requires-Python: >=3.8
Classifier: Intended Audience :: Information Technology
Classifier: Intended Audience :: Science/Research
Classifier: License :: OSI Approved :: MIT License
Classifier: Programming Language :: Python :: 3.10
Classifier: Programming Language :: Python :: 3.11
Classifier: Programming Language :: Python :: 3.8
Classifier: Programming Language :: Python :: 3.9
Classifier: Topic :: Scientific/Engineering :: GIS
Requires-Dist: pydantic_settings~=2.0
Requires-Dist: starlette-cramjam<0.4,>=0.3
Requires-Dist: titiler.core<0.14,>=0.13.0
Provides-Extra: dev
Requires-Dist: pre-commit; extra == "dev"
Provides-Extra: test
Requires-Dist: pytest; extra == "test"
Requires-Dist: pytest-cov; extra == "test"
Requires-Dist: pytest-asyncio; extra == "test"
Requires-Dist: httpx; extra == "test"
Project-URL: Homepage, https://github.com/developmentseed/titiler-image
Project-URL: Issues, https://github.com/developmentseed/titiler-image/issues
Project-URL: Source, https://github.com/developmentseed/titiler-image
